{
    "标题": "全国学校疫情防控能力提升培训预告",
    "发布时间": "2023-01-12",
    "网址": "http://www.moe.gov.cn/jyb_xwfb/gzdt_gzdt/s5987/202301/t20230112_1039161.html",
    "来源": "教育部",
    "责任编辑": "俞曼悦",
    "内容": "　　为贯彻落实2023年1月5日全国教育系统疫情防控工作视频会议精神和《学校新型冠状病毒感染防控工作方案》，指导学校科学有效应对疫情，确保转段过渡期平稳有序，经研究，决定开展全国学校疫情防控能力提升培训。\n　　一、培训主题\n　　深入贯彻落实习近平总书记关于疫情防控重要指示精神，“保健康、防重症、护校园”，进一步提高“乙类乙管”下学校应对疫情能力，利用寒假窗口期做好春季开学各方面准备，最大程度保障师生健康，最大限度降低疫情对教育教学影响，全力确保春季学期正常开学。\n　　二、培训项目、时间、对象及内容\n　　（一）全国高校健康驿站建设管理专项培训。2023年1月13日（周五）上午9：00—12：00，面向各高校分管负责同志，健康驿站各专项工作组以及学校校医院（卫生室）等有关部门负责同志以及相关工作人员，举办高校健康驿站视频直播培训。培训内容包括《普通高等学校健康驿站建设管理指引》技术解读，高校健康驿站建设管理、运行经验分享，人员入站研判、在站健康管理、转运救治、出站康复指导等。\n　　（二）全国中小学疫情防控专项培训。2023年1月13日（周五）下午2：00—5：00。面向各中小学校健康副校长、校医、园医、保健教师和全国学校卫生工作者，举办全国中小学校疫情防控视频直播培训。培训内容包括中小学校应对新冠病毒感染疫情的政策解读，儿童青少年新冠病毒感染的临床救治、日常用药、家庭照护，校园一线防疫技能等。\n　　三、培训方式\n　　通过“北京大学儿童青少年卫生研究所”和“全国中小学健康教育教指委”视频号开展视频直播（可通过微信公众号或视频号搜索“北京大学儿童青少年卫生研究所” 或“全国中小学健康教育教指委”，关注即可观看视频直播，也可直接扫描下方二维码进行预约观看），参加培训的人员提前10分钟上线，培训结束后提供培训视频录播回放链接。\n\n1月13日上午：高校健康驿站建设管理专项培训会直播二维码\n（左右均可）\n\n\n1月13日下午：中小学疫情防控专项培训会直播二维码\n（左右均可）"
}