{
    "标题": "2023年全国教育经费执行情况统计快报",
    "发布时间": "2024-07-22",
    "网址": "http://www.moe.gov.cn/jyb_xwfb/gzdt_gzdt/s5987/202407/t20240722_1142296.html",
    "来源": "教育部",
    "责任编辑": "刘洋",
    "内容": "　　根据《教育部 国家统计局 财政部关于加强和完善教育经费统计工作的意见》（教财〔2016〕6号）有关要求，现将2023年全国教育经费初步统计情况公布如下：\n　　一、全国教育经费投入情况\n　　2023年，全国教育经费总投入为64595亿元，比上年增长5.3%。其中，国家财政性教育经费（主要包括一般公共预算安排的教育经费，政府性基金预算安排的教育经费，国有及国有控股企业办学中的企业拨款，校办产业和社会服务收入用于教育的经费等）为50433亿元，比上年增长4.0%。\n　　二、各级教育经费投入情况\n　　教育经费在各级教育间的分配情况为：\n　　1.全国学前教育经费总投入为5382亿元，比上年增长4.7%。\n　　2.全国义务教育经费总投入为28427亿元，比上年增长6.0%。\n　　3.全国高中阶段教育经费总投入为10154亿元，比上年增长6.2%。其中，中等职业教育经费总投入为3309亿元，比上年增长2.1%。\n　　4.全国高等教育经费总投入为17640亿元，比上年增长7.6%。其中，普通高职高专教育经费总投入为3630亿元，比上年增长7.1%。\n　　5.全国其他教育经费总投入2992亿元，比上年下降13.0%。\n　　三、各级教育生均教育经费支出情况\n　　2023年全国幼儿园、普通小学、普通初中、普通高中、中等职业学校、普通高等学校生均教育经费总支出情况是：\n　　1.全国幼儿园为16243元，比上年增长8.8%。\n　　2.全国普通小学为15895元，比上年增长4.3%。\n　　3.全国普通初中为22054元，比上年增长2.7%。\n　　4.全国普通高中为25811元，比上年增长3.8%。\n　　5.全国中等职业学校为24839元，比上年增长0.7%。\n　　6.全国普通高等学校为40721元，比上年增长3.9%。"
}