{
    "标题": "教育部领导春节前慰问老同志",
    "发布时间": "2022-02-17",
    "网址": "http://www.moe.gov.cn/jyb_xwfb/gzdt_gzdt/moe_1485/202202/t20220217_599948.html",
    "来源": "《中国教育报》",
    "责任编辑": "曹建",
    "内容": "　　本报讯（记者 焦新）农历壬寅新年来临之际，教育部党组书记、部长怀进鹏与部党组成员分别慰问了教育部机关27位离退休老部长、部分离休老同志、著名老专家，为他们送上新春祝福。\n　　1月28日，怀进鹏分别与张孝文、柳斌、张保庆3位老部长通电话，代表部党组向他们致以节日问候和新春祝福，感谢他们为教育事业作出的贡献和对教育工作的支持，祝愿他们节日快乐、健康长寿。老部长们对过去一年来部党组团结带领教育系统全体同志，坚持以习近平新时代中国特色社会主义思想为指导，坚持从政治上看教育、从民生上抓教育、从规律上办教育，着力把习近平总书记关于教育的重要论述有效转化为教育发展导向、政策举措和工作方法，推动教育高质量发展给予充分肯定。他们感谢部党组对离退休干部工作的高度重视和对老同志的关心关怀，并表示将一如既往地关注和支持教育事业的发展，祝愿教育事业在新的一年汲取建党百年智慧力量，弘扬伟大建党精神，以实际行动和优异成绩迎接党的二十大胜利召开。\n　　1月30日，怀进鹏以视频方式出席老同志迎春联欢团拜并致辞，向老部长、老同志表达新春祝福。部党组成员孙尧、田学军、翁铁慧、钟登华、吴道槐、郑富芝、宋德民也分别慰问了部分老部长、老同志。部内各司局共慰问离退休老同志800余人次，做到全覆盖。"
}