{
    "标题": "外语中文译写规范部际联席会议专家委员会发布第十三批推荐使用外语词中文译名",
    "发布时间": "2022-05-12",
    "网址": "http://www.moe.gov.cn/jyb_xwfb/gzdt_gzdt/s5987/202205/t20220512_626970.html",
    "来源": "教育部",
    "责任编辑": "曹建",
    "内容": "　　近日，外语中文译写规范部际联席会议专家委员会审议通过第十三批12组推荐使用外语词中文译名。\n　　本次拟推荐使用的外语词中文译名，以广电行业为主要范围，选自《中国广播电影电视发展报告》（2018-2020）、《中国视听新媒体发展报告》（2018-2020）等。中文译名及用例均主要来自“人民网”“光明网”“新华网”、国家广播电视总局官网以及各地广播电视机构的专业部门网站。审议会专家认为，第十三批译名筛选工作细致、方法科学，在网络语料和数据库核查分析的基础上，充分征询专家和相关行业部门意见，兼顾了译名的科学性和通用性，有利于译名的推广应用。 \n　　外语中文译写规范部际联席会议专家委员会推荐在社会生活各个领域使用规范的外语词中文译名。\n　　附件：第十三批推荐使用外语词中文译名表"
}