{
    "标题": "教育部举办义务教育优质均衡先行创建研讨班",
    "发布时间": "2023-12-19",
    "网址": "http://www.moe.gov.cn/jyb_xwfb/gzdt_gzdt/s5987/202312/t20231219_1095283.html",
    "来源": "教育部",
    "责任编辑": "曹建",
    "内容": "　　12月11日至15日，教育部在杭州举办义务教育优质均衡先行创建研讨班，深入学习党的二十大精神和习近平总书记关于教育的重要论述，推动落实党中央、国务院关于义务教育优质均衡发展和城乡一体化决策部署，交流研讨义务教育优质均衡先行创建工作经验和做法，明确下一步工作要求和思路举措。\n　　研讨班系统传达了全国义务教育优质均衡发展现场推进会精神，推动各地切实增强办好义务教育的责任感使命感，深刻把握推进义务教育优质均衡发展和城乡一体化的目标方向和重点任务，着力落实立德树人根本任务、发展素质教育、提高均衡发展水平、破解人民群众“急难愁盼”问题、深化教育综合改革、加强教师队伍建设，切实办好更加公平更高质量的义务教育。\n　　研讨班设置了专题报告、地方经验分享、分组交流研讨等环节。教育部基础教育司、教育督导局有关负责同志，中国财政科学研究院、教育部基础教育质量监测中心相关专家学者参加授课。天津市、上海市、浙江省嘉兴市、四川省成都市青羊区、河南省洛阳市西工区等14个省、市、县级教育行政部门的负责同志介绍了本地区推进义务教育优质均衡发展的经验做法。参训学员围绕贯彻落实全国义务教育优质均衡发展现场推进会精神，就义务教育优质均衡发展工作重点难点问题、解决策略及抓好先行创建工作等进行了分组交流研讨。\n　　各省（区、市）、新疆生产建设兵团、计划单列市教育行政部门基础教育处有关负责同志，全国135个义务教育优质均衡先行创建县以及部分乡村振兴重点帮扶县教育行政部门负责同志等近200人参加了研讨班。"
}