{
    "标题": "教育部、公安部联合召开全国中小学幼儿园安全工作视频会议",
    "发布时间": "2022-04-28",
    "网址": "http://www.moe.gov.cn/jyb_xwfb/gzdt_gzdt/moe_1485/202204/t20220428_623074.html",
    "来源": "教育部",
    "责任编辑": "曹建",
    "内容": "　　近日，教育部、公安部联合召开全国中小学幼儿园安全工作视频会议，贯彻落实习近平总书记关于安全生产工作的重要指示批示精神和全国安全生产电视电话会议部署要求，部署做好2022年中小学幼儿园安全工作。教育部党组成员、副部长郑富芝和公安部治安管理局局长李京生出席会议并讲话。\n　　会议指出，校园安全牵动亿万家庭和全社会最敏感神经，做好校园安全工作责任重大，各地必须突出重点，抓住关键，不断提高工作针对性和实效性。一是高度重视重在常抓。要贯穿全时段，覆盖全场所，形成时时抓、处处抓、人人抓的安全工作格局。二是全面排查重在查漏。要定期进行全面排查，重点排查苗头性问题和容易忽视的问题，不放过任何一个漏洞。三是强化防护重在达标。要按照规定标准加强人防、物防、技防建设，尚未达标的地方要确保在本学期内全面达标，并有效运行。四是应急处置重在稳妥。要快速反应，查清原委，处置精准，实事求是发布权威信息，及时回应社会关切。五是健全制度重在明责。要建立全覆盖的安全管理制度，分级分类明确责任，抓好督促落实。\n　　会议要求，各地要加快推进校园安防建设，强化校园周边巡逻防控，严打涉校违法犯罪，筑牢校园安全防控屏障，以实际行动迎接党的二十大胜利召开。\n　　会议通报了中小学幼儿园安全工作有关情况，福建、江西、湖南公安厅和重庆、安徽、广东教育厅（教委）作了交流发言。中央和国家有关部门司局负责同志参会。"
}