{
    "标题": "《汉语拼音方案》颁布65周年纪念暨学术研讨会在北京大学举办",
    "发布时间": "2023-06-29",
    "网址": "http://www.moe.gov.cn/jyb_xwfb/gzdt_gzdt/s5987/202306/t20230629_1066372.html",
    "来源": "教育部",
    "责任编辑": "曹建",
    "内容": "　　为深入贯彻落实党的二十大精神，深刻把握“两个结合”，加大国家通用语言文字推广力度，6月28日，在教育部语用司指导下，国家语言文字推广基地（北京大学）和教育部语用所联合举办了《汉语拼音方案》颁布65周年纪念暨学术研讨会。\n　　会议以“《汉语拼音方案》与中国式现代化”为主题，回顾总结其历史贡献和成功经验，对新时代新征程进一步发挥汉语拼音作用进行了深入研讨。\n　　会议认为，汉语拼音方案是中国语言文字事业发展的一面旗帜，65年来，汉语拼音已经融入教育、科技、文化以及社会生产生活的方方面面，成为以语文现代化助力国家现代化建设的成功典范。在全面推进中国式现代化建设的新征程上，要充分发挥汉语拼音在推动教育高质量发展、推进建设中华民族现代文明、赋能数字中国建设、满足人民群众社会生活需求、促进高水平对外开放中的重要作用，助力教育强国、科技强国、文化强国建设，为推进中国式现代化贡献更磅礴的“语言之力”。\n　　工业和信息化部中国电子技术标准化研究院、民政部地名研究所、中国语文现代化学会有关负责同志在开幕式上发言。国家语委咨询委员、北京大学教授陆俭明等专家学者作主旨发言。当天下午，还举办了以汉语拼音规范应用和创新使用、汉语拼音助力数字中国建设、汉语拼音国际传播与应用为主题的平行论坛，20余位专家学者对有关问题进行了深入探讨。\n　　教育部语用司、语信司、北京市教委有关同志以及国家语言文字推广基地代表、有关专家学者等参会。"
}