{
    "标题": "2020年全国教育经费执行情况统计公告发布",
    "发布时间": "2021-11-30",
    "网址": "http://www.moe.gov.cn/jyb_xwfb/gzdt_gzdt/s5987/202111/t20211130_583350.html",
    "来源": "教育部",
    "责任编辑": "曹建",
    "内容": "　　教育部、国家统计局、财政部近日发布了2020年全国教育经费执行情况统计公告。公告显示，2020年全国教育经费总投入为53033.87亿元，比上年增长5.69%。其中，国家财政性教育经费为42908.15亿元，比上年增长7.15%，占GDP比例为4.22%。“十三五”期间持续做到“不低于4%”，这是自2012年以来连续第九年做到“不低于4%”。\n　　“十三五”期间，全国一般公共预算教育支出累计16.06万亿元，年均增长7.02%，2020年达到36310.47亿元，比2015年增长40.4%。全国幼儿园生均一般公共预算教育经费年均增长12.3%，2020年达到9410.76元，比2015年增长76.48%；全国普通小学生均一般公共预算教育经费年均增长5.08%，2020年达到12330.58元，比2015年增长28.13%；全国普通初中生均一般公共预算教育经费年均增长5.81%，2020年达到17803.6元，比2015年增长32.64%；全国普通高中生均一般公共预算教育经费年均增长8.45%，2020年达到18671.83元，比2015年增长49.99%；全国中等职业学校生均一般公共预算教育经费年均增长5.56%，2020年达到17446.93元，比2015年增长31.05%；全国普通高等学校生均一般公共预算教育经费年均增长2.89%，2020年达到22407.39元，比2015年增长15.33%。"
}